hjimi_tools/__init__.py
hjimi_tools/convert_file_encoder.py
hjimi_tools/copy_files.py
hjimi_tools/create_c_project.py
hjimi_tools/file_collector.py
hjimi_tools/setup_package.py
hjimi_tools-0.1.2.dist-info/LICENSE
hjimi_tools-0.1.2.dist-info/METADATA
hjimi_tools-0.1.2.dist-info/WHEEL
hjimi_tools-0.1.2.dist-info/top_level.txt
hjimi_tools-0.1.2.dist-info/RECORD
