Metadata-Version: 2.2
Name: hjimi_tools
Version: 0.1.2
Summary: hjimi_tools is a versatile utility package for Python and C project setup, file management, and encoding conversion.
Author-email: wenquanshan <wenquanshan@sximi.com>
License: MIT
Project-URL: Homepage, https://github.com/zidanewenqsh/hjimi_utils
Project-URL: Documentation, https://github.com/zidanewenqsh/hjimi_utils/wiki
Project-URL: Bug_Tracker, https://github.com/zidanewenqsh/hjimi_utils/issues
Project-URL: Source, https://github.com/zidanewenqsh/hjimi_utils
Keywords: Python packaging,C project setup,file management,encoding conversion,utilities
Classifier: Development Status :: 4 - Beta
Classifier: Intended Audience :: Developers
Classifier: Topic :: Software Development :: Build Tools
Classifier: Programming Language :: Python :: 3
Classifier: License :: OSI Approved :: MIT License
Classifier: Operating System :: OS Independent
Requires-Python: >=3.9
License-File: LICENSE
Provides-Extra: dev
Requires-Dist: pytest>=7.0; extra == "dev"
Requires-Dist: twine>=4.0; extra == "dev"
